gendocker/__init__.py
gendocker/gendocker.py
gendocker-1.0.4.dist-info/METADATA
gendocker-1.0.4.dist-info/WHEEL
gendocker-1.0.4.dist-info/top_level.txt
gendocker-1.0.4.dist-info/RECORD
