Metadata-Version: 2.1
Name: gendocker
Version: 1.0.4
Summary: Package gendocker
Home-page: UNKNOWN
Author: jaytrairat
Author-email: <jay.trairat@gmail.com>
License: UNKNOWN
Keywords: jaytrairat
Platform: UNKNOWN
Classifier: Programming Language :: Python :: 3
